rudder/__init__.py
rudder/__main__.py
rudder/core.py
rudder/rudder.py
rudder/runner.py
rudder/data/logging.yml
rudder/states/__init__.py
rudder/states/creation.py
rudder/states/innvocation.py
rudder/states/parseresults.py
rudder/states/state.py
rudder/utils/__init__.py
rudder/utils/exceptions.py
rudder/utils/logger.py
rudder/utils/version.py
rudder-0.3.2.dist-info/LICENSE.md
rudder-0.3.2.dist-info/METADATA
rudder-0.3.2.dist-info/WHEEL
rudder-0.3.2.dist-info/entry_points.txt
rudder-0.3.2.dist-info/top_level.txt
rudder-0.3.2.dist-info/RECORD
