Metadata-Version: 2.1
Name: rudder
Version: 0.3.2
Summary: A Python package to execute code remotely to multiple operating system platforms
Home-page: https://github.com/MSAdministrator/rudder
Author: MSAdministrator
Author-email: rickardja@live.com
License: MIT
Keywords: rudder,winrm,ssh,cmd,powershell
Platform: UNKNOWN
Requires-Python: >3.6
Requires-Dist: paramiko (==2.7.2)
Requires-Dist: fire (==0.4.0)
Requires-Dist: pypsrp (==0.5.0)
Requires-Dist: pyyaml (==5.4.1)
